Topsis_Yash_101803617
