Metadata-Version: 1.1
Name: Topsis-Yash-101803617
Version: 0.0.2
Summary: A Python package implementing TOPSIS technique.
Home-page: https://pypi.org/project/Topsis-Yash-101803617/0.0.1/
Author: Yash Shukla
Author-email: yash981815@gmail.comm
License: MIT
Platform: UNKNOWN
Classifier: License :: OSI Approved :: MIT License
Classifier: Programming Language :: Python :: 3
Classifier: Programming Language :: Python :: 3.4
Classifier: Programming Language :: Python :: 3.5
Classifier: Programming Language :: Python :: 3.6
Classifier: Programming Language :: Python :: 3.7
